numcodecs_wasm-0.2.1.dist-info/METADATA
numcodecs_wasm-0.2.1.dist-info/WHEEL
numcodecs_wasm-0.2.1.dist-info/licenses/LICENSE
numcodecs_wasm/.gitignore
numcodecs_wasm/__init__.py
numcodecs_wasm/_wasm.abi3.so
numcodecs_wasm/py.typed
numcodecs_wasm-0.2.1.dist-info/RECORD
