Metadata-Version: 2.4
Name: numcodecs_wasm
Version: 0.2.1
Classifier: Programming Language :: Rust
Classifier: Programming Language :: Python :: Implementation :: CPython
Classifier: Programming Language :: Python :: Implementation :: PyPy
Requires-Dist: numcodecs>=0.13.0,<0.17
Requires-Dist: numcodecs-observers~=0.1.1
Requires-Dist: numpy~=2.0
Requires-Dist: typing-extensions~=4.6
License-File: LICENSE
Summary: numcodecs compression for codecs compiled to WebAssembly
Author-email: Juniper Tyree <juniper.tyree@helsinki.fi>
Maintainer-email: Juniper Tyree <juniper.tyree@helsinki.fi>
Requires-Python: >=3.10
